[
    {
        "supermercado": "Jumbo",
        "titulo": "40% Off en Perfumería, Almacén",
        "descripcion": "OFERTAS dela SEMANAA) NuEvA TECNOLOGLa Afyimo Guidado Defiaras #u85   gs295 ALMACÉN, BEBIDAS, FRESCOS, 140% PERFUMERIA Y LIMPIEZA VÁLIDO DEL 05/01 AL 08/01. SELECCIONADOS. [leGa skip BIO-ENZIMAS AgAr dedioc Terrabusi 5848 5sL cehi EXCLUSIVO ONLINE Diente Blancos ua(vintvig suinne UtuV ! SENSITIVE Iut (ioforn FAnynoouiuu Blanqueadora Colgate Cant Moto 1009 (73mu Cheel degcreNdk Hasta 40% Almacén, Bebidas, Frescos, Perfumería y Limpieza Hasta 40% Almacén, Bebidas, Frescos, Perfumería y Limpieza",
        "categoria": [
            "🧹 Limpieza",
            "🧴 Perfumería y Bebé",
            "📺 Electro y Tecno"
        ],
        "link": "https://www.jumbo.com.ar/56043?map=productClusterIds&evento=eds",
        "imagen": "https://jumboargentinaio.vtexassets.com/assets/vtex.file-manager-graphql/images/5d01addd-5012-4a63-b741-5c156c9b2e90___c3acc5a958b82dbc326de9aa85302c88.webp",
        "fecha": "2026-01-08"
    },
    {
        "supermercado": "Jumbo",
        "titulo": "2x1 en Cervezas",
        "descripcion": "VERANOy PICADITA PATAGONIA Kh247 HASTA CERVEZAS 2x1 Y SNACKS PRODUCTOS SELECCIONADOS. (EXCESOEN Grasas ExcESOE Grasas EN TotalES SaTuRaDAS| wisiheg[ (s [ExcESO SoDio EN EXCESQ PATAGONIA Calorias EN PAPA l EXCLUSIVO ONLINE CHIP 'SUPER 10ve7e@ MEC 24.7 PRINATrO VÁLIDODEL05/0IAL08/01. BEBER CONMODERACIÓN Hasta 2x1 en Cerveza y Snacks Hasta 2x1 en Cerveza y Snacks",
        "categoria": [
            "🍷 Bebidas"
        ],
        "link": "https://www.jumbo.com.ar/56034?map=productClusterIds",
        "imagen": "https://jumboargentinaio.vtexassets.com/assets/vtex.file-manager-graphql/images/00050a0d-49a9-4adf-afc5-a2d427afc354___9a10a69d413bf65ede2570447611c56a.webp",
        "fecha": "2026-01-08"
    },
    {
        "supermercado": "Jumbo",
        "titulo": "Oferta en Milanesas, Corte Nalga",
        "descripcion": "más fresco más rico MILANESA DE NALGA $16999 DE NOVILLITO VÁLIDO DEL 05/01 AL 08/01 PRECIO SIN IMPUESTOS: $15,383.71 Milanesa de nalga y más Milanesa de nalga y más",
        "categoria": [
            "🥩 Carnicería"
        ],
        "link": "https://www.jumbo.com.ar/56044?map=productClusterIds",
        "imagen": "https://jumboargentinaio.vtexassets.com/assets/vtex.file-manager-graphql/images/d0bb4e52-556b-4ce2-9bd1-609be558edb8___46c24fe7a0b449ab4a833b1dd9e229a1.webp",
        "fecha": "2026-01-08"
    },
    {
        "supermercado": "Jumbo",
        "titulo": "Hasta 50% Off en Hasta 50% Y Hasta 3 Csi En Juguetería Hasta 50% Y ",
        "descripcion": "Regalos de Reyes 13 SUOTASRÉS 150% cCnCo pay CRÉDITO 160% '12 'SNERÉS VÁLIDO DEL 30/12 AL 08/01. PRODUCTOS SELECCIONADOS . IEhT MyyEavg {ooeri Turngou Pinypon fncooJeweg @ypao' #hing Hasta 50% y Hasta 3 CSI en Juguetería Hasta 50% y Hasta 3 CSI en Juguetería",
        "categoria": [
            "🍝 Almacén"
        ],
        "link": "https://www.jumbo.com.ar/55362?map=productClusterIds",
        "imagen": "https://jumboargentinaio.vtexassets.com/assets/vtex.file-manager-graphql/images/6fe1c69e-bfd6-479b-998a-0c8a06cb8b40___6911bae93bb356d1615849626e5d9b19.webp",
        "fecha": "2026-01-08"
    },
    {
        "supermercado": "Jumbo",
        "titulo": "Promoción Bancaria",
        "descripcion": "Los jueves cencopay -25%+3 cuotas EN BEBIDAS SIN ALCOHOL, CRÉDITO (2) FIDEOS, PASTAS FRESCAS, sin interés ARROZ Y iMUCHO MÁS! SIN TOPE DE DESCUENTO (2) TNA: 0,0% TEA: 0,0% CFTNA: 0,0% PROMOCIÓN VÁLIDA DEL 01/01/2026 AL 31/01/2026. VER LEGALES Y EXCLUSIONES EN CENCOPAY AR 25% en Bebidas y más 25% en Bebidas y más",
        "categoria": [
            "💳 Bancarias",
            "🍝 Almacén"
        ],
        "link": "https://www.jumbo.com.ar/53919?map=productClusterIds",
        "imagen": "https://jumboargentinaio.vtexassets.com/assets/vtex.file-manager-graphql/images/d8fad722-f8b9-4258-a25f-14c3a79c9434___74d3d1e1e4309bb95da3e17adeb4b5c6.jpg",
        "fecha": "2026-01-08"
    },
    {
        "supermercado": "Jumbo",
        "titulo": "2do al 70% en Jumbo Prime | Hasta 2Do Al 70% Jumbo Prime | Hasta",
        "descripcion": "Del 7al 13 de enero DESCUENTOS EXCLUSIVOS PARASOCIOS prime Es momento de ser HASTA 2DO AL % [Bijyf8 70 itric 1004 DTO MARAYIAL Pr|me karon 1@ EN CERVEZAS Y cuguula _ ineken BuHoor] JUGOS REFRIGERADOS Mnnnly 7hfff BFR?U BEBER CON MODERACIÓN. PROHIBIDA SUVENTA A MENORES DE 18 AÑOS Jumbo Prime | Hasta 2do al 70% Jumbo Prime | Hasta 2do al 70%",
        "categoria": [
            "🍝 Almacén"
        ],
        "link": "https://www.jumbo.com.ar/eventos/descuentos-jumbo-prime",
        "imagen": "https://jumboargentinaio.vtexassets.com/assets/vtex.file-manager-graphql/images/98b23ceb-22c7-4a2e-9bea-612600181535___04ba4ca801c7c67229fa6d60c3670ddd.png",
        "fecha": "2026-01-08"
    },
    {
        "supermercado": "Jumbo",
        "titulo": "Hasta 50% Off en Hogar",
        "descripcion": "iRENOVÁ TODO! OPORTUNIDADES domo ESPECIAL HOGAR 75 ChAMex Crooo 1 150% VÁLIDO DEL 07/01 AL 20/01. PRODUCTOS SELECCIONADOS. 1 1 1 1 1 Hasta 50% | Especial Hogar Hasta 50% | Especial Hogar",
        "categoria": [
            "🏠 Hogar y Bazar"
        ],
        "link": "https://www.jumbo.com.ar/54930?map=productClusterIds",
        "imagen": "https://jumboargentinaio.vtexassets.com/assets/vtex.file-manager-graphql/images/a404fc8a-929d-4f37-928d-01d8bc7e7e5f___c2e9acb3f9aa4a47d00420abe8da6d35.webp",
        "fecha": "2026-01-08"
    },
    {
        "supermercado": "Jumbo",
        "titulo": "35% Off en Jabón Ropa",
        "descripcion": "Único diseñado para   ciclo corto skip E X P E { X 35% DTO Freegyr^ 4235z4 949nr? Nuve skip Mivo ETx 0 skip skip Cortos CICLos  Cortos Ciclos , OClaro Delavedo Cortos Ciclos , Bilevado 6 Fa 4l4 5a  ",
        "categoria": [
            "🧹 Limpieza"
        ],
        "link": "https://www.jumbo.com.ar/skip?_q=skip&map=ft",
        "imagen": "https://jumboargentinaio.vtexassets.com/assets/vtex.file-manager-graphql/images/fab02fc6-cae9-4761-8ee2-16f56c344b8d___00b07da857cf7d28c328a80975de7f0c.jpg",
        "fecha": "2026-01-08"
    },
    {
        "supermercado": "Jumbo",
        "titulo": "40% Off en Limpiadores",
        "descripcion": "nuevo NUEVO (Cif (Cif ACTIVEGEL ACTIVEGEL 40% DTO xio MAS ESPUMA  ",
        "categoria": [
            "🧹 Limpieza"
        ],
        "link": "https://www.jumbo.com.ar/55995?map=productClusterIds",
        "imagen": "https://jumboargentinaio.vtexassets.com/assets/vtex.file-manager-graphql/images/61c56d73-f56e-4831-a5e5-6e89d67f84be___e9af54f3038f00c422e4f458246f29e7.jpg",
        "fecha": "2026-01-08"
    },
    {
        "supermercado": "Jumbo",
        "titulo": "35% Off en Varios Productos",
        "descripcion": "Babysec Nuevo Muevoi Hpehasa Ladysoft. 1135% Babysec Babysec 0304 XXG ULIKA sott Ladysoft| Ladysoft Ladysoft Ladysoft Babysec biaros ULTRA Tra Supcr Premium Comprar  ",
        "categoria": [
            "🍝 Almacén"
        ],
        "link": "https://www.jumbo.com.ar/babysec%20ladysoft?_q=babysec%20ladysoft&fuzzy=auto&initialMap=ft&initialQuery=babysec%20ladysoft&map=brand,brand,ft&operator=or&query=/babysec/ladysoft/babysec%20ladysoft&searchState",
        "imagen": "https://jumboargentinaio.vtexassets.com/assets/vtex.file-manager-graphql/images/36747346-2638-44c7-b2ec-77b09a0e6021___5ca025f910c356fb5f80d430f59789ca.jpg",
        "fecha": "2026-01-08"
    },
    {
        "supermercado": "Jumbo",
        "titulo": "30% Off en Insecticidas, Jabón Ropa",
        "descripcion": "130% EXCLUSIVO ONLINE 48953 Fuyi Sun MatA Insecticida Mosourros Moscas skip VÁLIDO DEL 03@81@cowepos : Limpieza ",
        "categoria": [
            "🧹 Limpieza"
        ],
        "link": "https://www.jumbo.com.ar/56041?map=productClusterIds",
        "imagen": "https://jumboargentinaio.vtexassets.com/assets/vtex.file-manager-graphql/images/2456da12-8daf-4587-869d-1bdd132eab78___1443592136bd02cdd0fc2e519b0672b7.webp",
        "fecha": "2026-01-08"
    },
    {
        "supermercado": "Jumbo",
        "titulo": "2x1 en Cervezas Y Snacks ",
        "descripcion": "2x1 EXCLUSIVO ONLINE 1 Cuisines( Pafaconia 1 PAPA Lll CHIPS KECA SUPER Sar4s?bes VÁLIDO DEL 05/01 AL 08/01- SRT BEBER CON MODERACION, Cervezas y Snacks ",
        "categoria": [
            "🍝 Almacén"
        ],
        "link": "https://www.jumbo.com.ar/56039?map=productClusterIds",
        "imagen": "https://jumboargentinaio.vtexassets.com/assets/vtex.file-manager-graphql/images/f16524bf-bcc6-4f4f-82b6-680cff01c226___605e9f9edb2876af762fb8e64288eaaf.webp",
        "fecha": "2026-01-08"
    },
    {
        "supermercado": "Jumbo",
        "titulo": "2x1 en Café",
        "descripcion": "I2x1 EXCLUSIVO ONLINE Dq imyeys  0 NESCAFE 1 dolca VÁLIDO DEL 05/01 AL 08/01. SELECCIONADOS . 700 Desayuno ",
        "categoria": [
            "🍝 Almacén"
        ],
        "link": "https://www.jumbo.com.ar/56040?map=productClusterIds",
        "imagen": "https://jumboargentinaio.vtexassets.com/assets/vtex.file-manager-graphql/images/286e77c1-217f-493a-8eda-eb5a8aa15656___4a6f568176d00f783066f0a9f91ce710.webp",
        "fecha": "2026-01-08"
    },
    {
        "supermercado": "Jumbo",
        "titulo": "40% Off en Cuidado Personal, Perfumería",
        "descripcion": "140% EXCLUSIVO ONLINE 8 Dove Dove FZecoslraén jginat Keratina' VÁLIDö 05/01 AL 08 /07SELECCONADOS. Perfumería ",
        "categoria": [
            "🧴 Perfumería y Bebé"
        ],
        "link": "https://www.jumbo.com.ar/56042?map=productClusterIds",
        "imagen": "https://jumboargentinaio.vtexassets.com/assets/vtex.file-manager-graphql/images/089ebfbb-f6b4-4134-af0a-b7db9c0244e7___936e373c3660f4a9d069fc3f8fbf1960.webp",
        "fecha": "2026-01-08"
    },
    {
        "supermercado": "Jumbo",
        "titulo": "2x1 en Cervezas Y Snacks Cervezas Y Snacks",
        "descripcion": "HASTA 2x1 CERVEZAS Y SNACKS PRODUCTOS SELECCIONADOS. EXCLUSIVO ONLINE Patagonia Oosol JOTALEs Taasas (aSodi Satuvadas Cus s Wsihe (^ EESoen [PATAGONIA Sooio [#e525| PAPA CHIPS 24.7 Phmgies original VERLEGALES. BEBERCONMODERACIÓN Cervezas y Snacks Cervezas y Snacks",
        "categoria": [
            "🍝 Almacén"
        ],
        "link": "https://www.jumbo.com.ar/56034?map=productClusterIds",
        "imagen": "https://jumboargentinaio.vtexassets.com/assets/vtex.file-manager-graphql/images/4053b36d-9e0a-4dca-b749-ba7874a32c15___0e68d0c1e7b7664867cdaed4e02fcd6d.webp",
        "fecha": "2026-01-08"
    },
    {
        "supermercado": "Jumbo",
        "titulo": "Oferta en Cuidado Personal",
        "descripcion": "Nuevo Dove UVrepair & glow 1l40 % Óleo Bifásico FPC DTO Eefrr Ptese 7Oh de protección UV* uiuo \"Testeo irstrumentol con el uso regular luego 3Uscs  ",
        "categoria": [
            "🧴 Perfumería y Bebé"
        ],
        "link": "https://www.jumbo.com.ar/uv%20repair?_q=uv%20repair&map=ft",
        "imagen": "https://jumboargentinaio.vtexassets.com/assets/vtex.file-manager-graphql/images/1866a491-afc3-43d5-9cc2-c8c242e1452c___1c9be927db6f8d31e5e127078da13598.jpg",
        "fecha": "2026-01-08"
    }
]