[
    {
        "supermercado": "Coto",
        "titulo": "Oferta en Varios",
        "descripcion": "EN 1 PAGO Todos los Miércoles de Enero CoyunIoAL oood 15W DESCUENTO SIN TOPE DEREINTEGRO PARA Miembros de Nuestra Comunidad",
        "categoria": [
            "🍝 Almacén"
        ],
        "link": "https://www.cotodigital.com.ar/sitios/cdigi/",
        "imagen": "https://static.cotodigital3.com.ar/sitios/cdigi/static/content/images/cdigi/ofertas/cartridge/nuevahome/2025-01/images/15comuEne26.jpg",
        "fecha": "2026-01-14"
    },
    {
        "supermercado": "Coto",
        "titulo": "Oferta en Asado",
        "descripcion": "INGRESAR s10899 XKG prECIO Sik IpuESTOS NACIOHALES: $9.863,35 AsADo DE HovilLiTO, Cod,47979 s15399 X KG. PPER8 SHUPHEssH HACIONALES: $13.935,75 CoD. 47980",
        "categoria": [
            "🥩 Carnicería"
        ],
        "link": "https://www.cotodigital.com.ar/sitios/cdigi/categoria?_dyncharset=utf-8&Dy=1&Ntt=bannerasado9126",
        "imagen": "https://static.cotodigital3.com.ar/sitios/cdigi/static/content/images/cdigi/ofertas/cartridge/nuevahome/2025-01/images/asasovacio060126.jpg",
        "fecha": "2026-01-14"
    },
    {
        "supermercado": "Coto",
        "titulo": "Oferta en Pollo",
        "descripcion": "s5499 X KG PRECIO ANTERIOR: $ 6399 PRECIO SIN IMPUESTOS WACIOHALES: $ 5790,95 HUGGETSIMEDALLÓNISUPREMA DE POLLO COHGELADOS COD. 47459-47460-47461 610499 X KG PRECIO ANTERIOR: $ 11699 PRECIO SIN IMPUESTOS HACIOWALES: $ 10587,33 ROAST BEEF DE VoviLiITO , COD. 41384-47985 611499 X KG PRECIO ANTERIOR: $ 12699 PRECIO SIN IMPUESTOS WACIONALES: $ 11492,31 PALETA DE HovILLITO, CoD. 41395-47984",
        "categoria": [
            "🥩 Carnicería"
        ],
        "link": "https://www.cotodigital.com.ar/sitios/cdigi/categoria?_dyncharset=utf-8&Dy=1&Ntt=CarnesSemanal120126",
        "imagen": "https://static.cotodigital3.com.ar/sitios/cdigi/static/content/images/cdigi/ofertas/cartridge/nuevahome/2025-01/images/CarnesSemanal120126.jpg",
        "fecha": "2026-01-14"
    },
    {
        "supermercado": "Coto",
        "titulo": "Oferta en Perfumería",
        "descripcion": "ONLINE) EXCLUSIVO C HASTA EN PRODUCTOS DE 508 PERFUMERIA OFF S E L E C C 1 0 N A D 0 $ Hasta el 15 de enero",
        "categoria": [
            "🧴 Perfumería y Bebé"
        ],
        "link": "https://www.cotodigital.com.ar/sitios/cdigi/categoria?_dyncharset=utf-8&Dy=1&Ntt=perfumeriaEne26",
        "imagen": "https://static.cotodigital3.com.ar/sitios/cdigi/static/content/images/cdigi/ofertas/cartridge/nuevahome/2025-01/images/perfumeriaEne26.jpg",
        "fecha": "2026-01-14"
    },
    {
        "supermercado": "Coto",
        "titulo": "3x2 en Hamburguesas, Cerdo",
        "descripcion": "Prodactos marca 359 oood DESCUENTO EXCLUSIVO ONLINE {AMDURCNESAS Hamburguesas Dlter 1a de carne coid vacuna CoTo Cod: 231388 Ramhikftesas CBlvo 3x2 Hamburguesas de cerdo COTO Goro Cod: 260857 \"Ees Suprema Rebozada Congelada coTO Cod: 231383 Supremas 2xl cond",
        "categoria": [
            "🥩 Carnicería"
        ],
        "link": "https://www.cotodigital.com.ar/sitios/cdigi/categoria?_dyncharset=utf-8&Dy=1&Ntt=zona091025b",
        "imagen": "https://static.cotodigital3.com.ar/sitios/cdigi/static/content/images/cdigi/ofertas/cartridge/nuevahome/2025-01/images/zona091025.jpg",
        "fecha": "2026-01-14"
    },
    {
        "supermercado": "Coto",
        "titulo": "3x2 en Varios",
        "descripcion": "Dove original Ag z @9equadn Dove karite HASTA 3x2 Dove no reseca la piel como los jabones comunes. g Dove š 1 culdodo Inaulgente Pvr Promo DOVE Desde € 12-01-2026 al18-01-2026. Exclusivo Online , PARA MMS INFORMACIÓN CONDICIONES LIMITACIONES APLICABLES CONSULTE EN COTOCOMAR/LEGALES COMPRAR",
        "categoria": [
            "🍝 Almacén"
        ],
        "link": "https://www.cotodigital.com.ar/sitios/cdigi/categoria?_dyncharset=utf-8&Dy=1&Ntt=dove3x212126",
        "imagen": "https://static.cotodigital3.com.ar/sitios/cdigi/static/content/images/cdigi/ofertas/cartridge/nuevahome/2025-01/images/dove3x212126.jpg",
        "fecha": "2026-01-14"
    },
    {
        "supermercado": "Coto",
        "titulo": "2x1 en Varios",
        "descripcion": "Nuevo Dove HASTA Oove  Knnlco Óleo + Sérum Bifásico UV Repair & Glow ferúlico 2x1 70 COMPRAR Promo DOVE Desdc cl 12-01-2026 al18-01-2026 Exclusivo Onlinc. PARA MÁS INFORMACIÓN Y CONDICIONES 0 LIMITACIONES APLICABLES, CONSULTE EN COTOCOM AR/LEGALES",
        "categoria": [
            "🍝 Almacén"
        ],
        "link": "https://www.cotodigital.com.ar/sitios/cdigi/categoria?_dyncharset=utf-8&Dy=1&Ntt=dove2x112126",
        "imagen": "https://static.cotodigital3.com.ar/sitios/cdigi/static/content/images/cdigi/ofertas/cartridge/nuevahome/2025-01/images/dove2x112126.jpg",
        "fecha": "2026-01-14"
    },
    {
        "supermercado": "Coto",
        "titulo": "40% Off en Pasta Dental",
        "descripcion": "Colgate Total En 2026 cambiate a la prevención de Total HASTA 40% DESCUENTO \"\"PROMOCOLGATEVALIDA 3xclsivc ONUNE DEL 12 AL 18 DEENFRO PARA MÁS INFORMACIÓN Y CONDICIONES 0 LIMITACIONES APLICABLES; CONSULTE EN \"COTOCOM ARJILEGALES\" COMPRAR 'sathdmabrnonodoygfl Daozaiul Pnseuuoir  Imnarzi Colgate Jotal Colgate Jotal",
        "categoria": [
            "🧴 Perfumería y Bebé"
        ],
        "link": "https://www.cotodigital.com.ar/sitios/cdigi/categoria?_dyncharset=utf-8&Dy=1&Ntt=colgate120126",
        "imagen": "https://static.cotodigital3.com.ar/sitios/cdigi/static/content/images/cdigi/ofertas/cartridge/nuevahome//2025-01/images/colgate120126.jpg",
        "fecha": "2026-01-14"
    },
    {
        "supermercado": "Coto",
        "titulo": "Oferta en Pescadería",
        "descripcion": "202 En Tda nezara DTO. PESCADÉRÉA ExKLUSIYO",
        "categoria": [
            "🥩 Carnicería"
        ],
        "link": "https://www.cotodigital.com.ar/sitios/cdigi/categoria%3FDy%3D1&Nf%3Dproduct.startDate%257CLTEQ%2B1.7568576E12%257C%257Cproduct.endDate%257CGTEQ%2B1.7568576E12&Nr%3DAND%2528product.language%253Aespa%25C3%25B1ol%252Cproduct.sDisp_200%253A1004%252COR%2528product.siteId%253ACotoDigital%2529%2529&Ns%3Dproduct.TOTALDEVENTAS%257C1&Ntt%3Dpescaderia1107&format%3Djson",
        "imagen": "https://static.cotodigital3.com.ar/sitios/cdigi/static/content/images/cdigi/ofertas/cartridge/nuevahome/2025-01/images/pescaderia20octubre.jpg",
        "fecha": "2026-01-14"
    },
    {
        "supermercado": "Coto",
        "titulo": "15 Cuotas S/Int en Rodados, Muebles",
        "descripcion": "Del 8 al 14 de Enero EW PRODUCTOS SELECCIONADOS DE ELECTRO , LIBROS , AUTOMOTOR, BAZAR; 15 CUOTAS BLANQUERIA , CAMPING , ACCESORIOS DE SIN INTERÉS ILUMINACIOH , JUGUETERIA , RODADOS , JARDINERIA , MUEBLES, FERRETERIA, TARJETAS DE CRÉDITO ABONANDO CON Macro DEPORTES Y LIBRERIA. MACRO",
        "categoria": [
            "📺 Electro y Tecno",
            "🏠 Hogar y Bazar",
            "🧸 Juguetería"
        ],
        "link": "https://www.cotodigital.com.ar/sitios/cdigi/categoria?_dyncharset=utf-8&Dy=1&Ntt=macro159126",
        "imagen": "https://static.cotodigital3.com.ar/sitios/cdigi/static/content/images/cdigi/ofertas/cartridge/nuevahome/2025-01/images/15cuotasmacroEne26.jpg",
        "fecha": "2026-01-14"
    },
    {
        "supermercado": "Coto",
        "titulo": "Oferta en Electrodomésticos",
        "descripcion": "ELEGH LA PROMO QUE MAS TE GUSTE EXCLUSIVO ONLINE HASTA 2515 EN PRODUCTOS SELECCIONADOS DE 12 4O%@ cuotas sIN iNTERES DE DESCUENTO EN UM pago CON TARJETAS SELECCIONADAS EXCLUSIVO comuNIAD coto ELECTRODOMÉSTICOS",
        "categoria": [
            "💳 Bancarias",
            "📺 Electro y Tecno"
        ],
        "link": "https://www.cotodigital.com.ar/sitios/cdigi/categoria%3FDy%3D1&Nf%3Dproduct.startDate%257CLTEQ%2B1.7676576E12%257C%257Cproduct.endDate%257CGTEQ%2B1.7676576E12&Nr%3DAND%2528product.language%253Aespa%25C3%25B1ol%252Cproduct.sDisp_200%253A1004%252COR%2528product.siteId%253ACotoDigital%2529%2529&Ns%3Dproduct.TOTALDEVENTAS%257C1&Ntt%3Delectro030126b&format%3Djson",
        "imagen": "https://static.cotodigital3.com.ar/sitios/cdigi/static/content/images/cdigi/ofertas/cartridge/nuevahome/2025-01/images/electro221124.jpg",
        "fecha": "2026-01-14"
    },
    {
        "supermercado": "Coto",
        "titulo": "18 Cuotas S/Int en Varios",
        "descripcion": "18 CUOTAS SIN INTERÉS Macro",
        "categoria": [
            "💳 Bancarias"
        ],
        "link": "https://www.cotodigital.com.ar/sitios/cdigi/",
        "imagen": "https://static.cotodigital3.com.ar/sitios/cdigi/static/content/images/cdigi/ofertas/18CSImacro.png",
        "fecha": "2026-01-14"
    },
    {
        "supermercado": "Coto",
        "titulo": "50% Off en Lonas, Art. Playa",
        "descripcion": "50% EN UN PAGO DESCUENTO En playeros y lonas. 9 hASTA eL 15/01/2026, para mÁs HforMACtOH Y cohdicIoHES hpLiCabLES buscar eh excotocomarflegales SECCIOH ' ~rehovA Tu CasA\"",
        "categoria": [
            "🏠 Hogar y Bazar"
        ],
        "link": "https://www.cotodigital.com.ar/sitios/cdigi/categoria?_dyncharset=utf-8&Dy=1&Ntt=rtc02090126",
        "imagen": "https://static.cotodigital3.com.ar/sitios/cdigi/static/content/images/cdigi/ofertas/cartridge/nuevahome/2025-01/images/rtc02090126.jpg",
        "fecha": "2026-01-14"
    },
    {
        "supermercado": "Coto",
        "titulo": "40% Off en Varios",
        "descripcion": "HASTA 40% EN UN PAGO DESCUENTO En zuecos, ojotas, sandalias accesorios de verano sslccionaaoss hasta el 15/01/2026, para MAS HYFCRMACTO\" Y CoHDICIoHes apLiCAbLeS busCAR eH ex Coto Com arflegales seCCIOY \"rehova Tu ChSA\"",
        "categoria": [
            "🍝 Almacén"
        ],
        "link": "https://www.cotodigital.com.ar/sitios/cdigi/categoria?_dyncharset=utf-8&Dy=1&Ntt=rtc03090126",
        "imagen": "https://static.cotodigital3.com.ar/sitios/cdigi/static/content/images/cdigi/ofertas/cartridge/nuevahome/2025-01/images/rtc03090126.jpg",
        "fecha": "2026-01-14"
    },
    {
        "supermercado": "Coto",
        "titulo": "50% Off en Bazar Vidrio, Vasos y Copas",
        "descripcion": "50% EN UN PAGO DESCUENTO En vasos y copas de cristal y vidrio. hasta eL 15/01/2026, para MAS HFoRMACTOH Y CohDIcIoHES apLiCables busCaR eH ex coto comarflegales seCCION \"rehova TU CaSa\"",
        "categoria": [
            "🏠 Hogar y Bazar"
        ],
        "link": "https://www.cotodigital.com.ar/sitios/cdigi/categoria?_dyncharset=utf-8&Dy=1&Ntt=rtc04090126",
        "imagen": "https://static.cotodigital3.com.ar/sitios/cdigi/static/content/images/cdigi/ofertas/cartridge/nuevahome/2025-01/images/rtc04090126.jpg",
        "fecha": "2026-01-14"
    }
]